{
  "color": [
    {
      "name": "start_window_background",
      "value": "#FFFFFF"
    },
    {
      "name": "white",
      "value": "#FFFFFF"
    },
    {
      "name": "index_backgroundColor",
      "value": "#F1F3F5"
    },
    {
      "name": "slide_selectedColor",
      "value": "#FF4B6A"
    },
    {
      "name": "blue_089ed9",
      "value": "#089ed9"
    },
    {
      "name": "detail_background",
      "value": "#000000"
    },
    {
      "name": "mini_text_font_color",
      "value": "#E6FFFFFF"
    }
  ]
}